iro/__about__.py
iro/__init__.py
iro/iro.py
iro/styles.py
iro-1.0.0.dist-info/METADATA
iro-1.0.0.dist-info/WHEEL
iro-1.0.0.dist-info/licenses/LICENSE
iro-1.0.0.dist-info/RECORD
