Metadata-Version: 2.3
Name: iro
Version: 1.0.0
Summary: Easy and powerful Colorizer for Python!
Author-email: Yamato Nagata <nagata@nagata.pro>
License: MIT License
License-File: LICENSE
Keywords: cli,color,colorize,colorizer,console,library,terminal,tool
Classifier: Development Status :: 5 - Production/Stable
Classifier: Environment :: Console
Classifier: Environment :: Other Environment
Classifier: Intended Audience :: Developers
Classifier: License :: OSI Approved :: MIT License
Classifier: Operating System :: OS Independent
Classifier: Programming Language :: Python
Classifier: Programming Language :: Python :: 3
Classifier: Topic :: Software Development :: Libraries
Classifier: Topic :: Software Development :: Libraries :: Python Modules
Classifier: Topic :: Terminals
Classifier: Topic :: Utilities
Requires-Python: >=3.8
